fabplugins
