Metadata-Version: 1.0
Name: fabplugins
Version: 1.0.1
Summary: Fabric plugins
Home-page: UNKNOWN
Author: Time Home
Author-email: timehome@corp.globo.com
License: MIT
Keywords: fabplugins
Platform: UNKNOWN
